ck_recursive_dataclass/__init__.py
ck_recursive_dataclass-0.1.2.dist-info/LICENSE
ck_recursive_dataclass-0.1.2.dist-info/METADATA
ck_recursive_dataclass-0.1.2.dist-info/WHEEL
ck_recursive_dataclass-0.1.2.dist-info/top_level.txt
ck_recursive_dataclass-0.1.2.dist-info/RECORD
