Metadata-Version: 2.2
Name: ck-recursive-dataclass
Version: 0.1.2
Summary: A Python library for recursively loading and updating dataclasses from nested dictionaries
Author-email: Charlie Kim <kimcharli@gmail.com>
License: MIT
Project-URL: Homepage, https://github.com/kimcharli/recursive_dataclasses
Project-URL: Repository, https://github.com/kimcharli/recursive_dataclasses.git
Project-URL: Issues, https://github.com/kimcharli/recursive_dataclasses/issues
Keywords: dataclasses,recursive,serialization,deserialization,nested
Classifier: Development Status :: 4 - Beta
Classifier: Intended Audience :: Developers
Classifier: License :: OSI Approved :: MIT License
Classifier: Programming Language :: Python :: 3
Classifier: Programming Language :: Python :: 3.11
Classifier: Programming Language :: Python :: 3.12
Classifier: Topic :: Software Development :: Libraries :: Python Modules
Requires-Python: >=3.11
License-File: LICENSE
Requires-Dist: typing-extensions>=4.0.0
Provides-Extra: test
Requires-Dist: pytest>=7.0.0; extra == "test"
Provides-Extra: dev
Requires-Dist: tox>=4.0.0; extra == "dev"
Requires-Dist: mypy>=1.0.0; extra == "dev"
Requires-Dist: ruff>=0.1.0; extra == "dev"
Requires-Dist: build; extra == "dev"
Requires-Dist: twine; extra == "dev"
